setup.cfg
setup.py
cryptolens/__init__.py
cryptolens/asset.py
cryptolens/config.py
cryptolens/database.py
cryptolens/dbmanager.py
cryptolens/initdb.py
cryptolens/main.py
cryptolens.egg-info/PKG-INFO
cryptolens.egg-info/SOURCES.txt
cryptolens.egg-info/dependency_links.txt
cryptolens.egg-info/entry_points.txt
cryptolens.egg-info/requires.txt
cryptolens.egg-info/top_level.txt
cryptolens/core/__init__.py
cryptolens/core/orderbook.py
cryptolens/daemon/__init__.py
cryptolens/daemon/processor.py
cryptolens/exchanges/__init__.py
cryptolens/exchanges/bitfinex.py
cryptolens/exchanges/bitmex.py
cryptolens/exchanges/bitrex.py
cryptolens/exchanges/exchange.py
cryptolens/exchanges/gdax.py
cryptolens/exchanges/poloniex.py
cryptolens/mvc/__init__.py
cryptolens/mvc/displaycommon.py
cryptolens/mvc/displayhome.py
cryptolens/mvc/displaymarket.py
cryptolens/tests/__init__.py
cryptolens/tests/bitfinex/__init__.py
cryptolens/tests/bitfinex/bitfinexprocessortests.py