Metadata-Version: 1.1
Name: cryptolens
Version: 0.1.12
Summary: Command line tool to monitor the prices of cryptocurrencies
Home-page: https://github.com/hkilian/cryptolens
Author: Harry Kilian
Author-email: harrykilian@gmail.com
License: MIT
Keywords: sample setuptools development
Platform: UNKNOWN
Classifier: Development Status :: 3 - Alpha
Classifier: Intended Audience :: Developers
Classifier: Topic :: Utilities
Classifier: License :: OSI Approved :: MIT License
Classifier: Programming Language :: Python :: 3
Classifier: Programming Language :: Python :: 3
Classifier: Programming Language :: Python :: 3.2
Classifier: Programming Language :: Python :: 3.3
Classifier: Programming Language :: Python :: 3.4
Classifier: Programming Language :: Python :: 3.5
